README.md
setup.py
xsqlpy/__init__.py
xsqlpy.egg-info/PKG-INFO
xsqlpy.egg-info/SOURCES.txt
xsqlpy.egg-info/dependency_links.txt
xsqlpy.egg-info/requires.txt
xsqlpy.egg-info/top_level.txt