Metadata-Version: 2.1
Name: xsqlpy
Version: 1.0.0
Summary: xsqlpy
Home-page: https://github.com/
Author: xsqlpy
Author-email: 1918118941@qq.com
Classifier: Programming Language :: Python :: 3
Classifier: License :: OSI Approved :: MIT License
Classifier: Operating System :: OS Independent
Requires-Python: >=3.11
Requires-Dist: marimo
Requires-Dist: duckdb
Requires-Dist: pandas
